disk_img_tool-0.1.2.data/data/share/doc/python-disk-img-tool/AUTHORS
disk_img_tool-0.1.2.data/data/share/doc/python-disk-img-tool/LICENSE
disk_img_tool-0.1.2.data/data/share/doc/python-disk-img-tool/README.md
disk_img_tool-0.1.2.data/scripts/disk-img-tool
diskimgtool/__init__.py
disk_img_tool-0.1.2.dist-info/LICENSE
disk_img_tool-0.1.2.dist-info/METADATA
disk_img_tool-0.1.2.dist-info/WHEEL
disk_img_tool-0.1.2.dist-info/top_level.txt
disk_img_tool-0.1.2.dist-info/RECORD
