Metadata-Version: 2.1
Name: disk-img-tool
Version: 0.1.2
Summary: Resize, list/get/put files and shell into raw disk images
Home-page: http://github.com/lpenz/disk-img-tool
Author: "Leandro Lisboa Penz"
Author-email: "lpenz@lpenz.org"
License: MIT
Classifier: Development Status :: 1 - Planning
Classifier: Environment :: Console
Classifier: License :: OSI Approved :: MIT License
Classifier: Operating System :: POSIX :: Linux
Classifier: Programming Language :: Python :: 3
Requires-Python: >=3.6
License-File: LICENSE
Provides-Extra: test
Requires-Dist: pytest ; extra == 'test'
Requires-Dist: pytest-cov ; extra == 'test'
